{
    "name": "temporal_country_inflation_rate",
    "prompt_templates": [
        "In {time}, the inflation rate of {subject} was, "
    ],
    "prompt_templates_zs": [
        "In {time}, what was the inflation rate of {subject}?",
        "What was the inflation rate of {subject} in {time}?"
    ],
    "properties": {
        "relation_type": "factual",
        "domain_name": "country",
        "range_name": "inflation rate",
        "symmetric": false
    },
    "samples": [
        {
            "subject": "United States",
            "object": "2.19",
            "time": "1999"
        },
        {
            "subject": "United States",
            "object": "3.38",
            "time": "2000"
        },
        {
            "subject": "United States",
            "object": "2.83",
            "time": "2001"
        },
        {
            "subject": "United States",
            "object": "1.59",
            "time": "2002"
        },
        {
            "subject": "United States",
            "object": "2.27",
            "time": "2003"
        },
        {
            "subject": "United States",
            "object": "2.68",
            "time": "2004"
        },
        {
            "subject": "United States",
            "object": "3.39",
            "time": "2005"
        },
        {
            "subject": "United States",
            "object": "3.23",
            "time": "2006"
        },
        {
            "subject": "United States",
            "object": "2.85",
            "time": "2007"
        },
        {
            "subject": "United States",
            "object": "3.84",
            "time": "2008"
        },
        {
            "subject": "United States",
            "object": "-0.36",
            "time": "2009"
        },
        {
            "subject": "Brazil",
            "object": "8.94",
            "time": "1999"
        },
        {
            "subject": "Brazil",
            "object": "6.00",
            "time": "2000"
        },
        {
            "subject": "Brazil",
            "object": "7.67",
            "time": "2001"
        },
        {
            "subject": "Brazil",
            "object": "8.44",
            "time": "2002"
        },
        {
            "subject": "Brazil",
            "object": "14.71",
            "time": "2003"
        },
        {
            "subject": "Brazil",
            "object": "6.60",
            "time": "2004"
        },
        {
            "subject": "Brazil",
            "object": "6.87",
            "time": "2005"
        },
        {
            "subject": "Brazil",
            "object": "3.14",
            "time": "2006"
        },
        {
            "subject": "Brazil",
            "object": "4.46",
            "time": "2007"
        },
        {
            "subject": "Brazil",
            "object": "5.90",
            "time": "2008"
        },
        {
            "subject": "Brazil",
            "object": "4.31",
            "time": "2009"
        },
        {
            "subject": "South Korea",
            "object": "0.81",
            "time": "1999"
        },
        {
            "subject": "South Korea",
            "object": "2.28",
            "time": "2000"
        },
        {
            "subject": "South Korea",
            "object": "4.08",
            "time": "2001"
        },
        {
            "subject": "South Korea",
            "object": "2.75",
            "time": "2002"
        },
        {
            "subject": "South Korea",
            "object": "3.57",
            "time": "2003"
        },
        {
            "subject": "South Korea",
            "object": "3.63",
            "time": "2004"
        },
        {
            "subject": "South Korea",
            "object": "2.77",
            "time": "2005"
        },
        {
            "subject": "South Korea",
            "object": "2.22",
            "time": "2006"
        },
        {
            "subject": "South Korea",
            "object": "2.53",
            "time": "2007"
        },
        {
            "subject": "South Korea",
            "object": "4.67",
            "time": "2008"
        },
        {
            "subject": "South Korea",
            "object": "2.76",
            "time": "2009"
        }
    ],
    "alias_time_templates": [
        {
            "year": "1996",
            "template": "In the year the Summer Olympics were held in Atlanta, {} was a member of sports team"
        },
        {
            "year": "1997",
            "template": "In the year the Champions League final was held in Munich, {} was a member of sports team"
        },
        {
            "year": "1998",
            "template": "In the year the Winter Olympics were held in Nagano, {} was a member of sports team"
        },
        {
            "year": "1999",
            "template": "In the year the Champions League final was held in Barcelona, {} was a member of sports team"
        },
        {
            "year": "2000",
            "template": "In the year the Summer Olympics were held in Sydney, {} was a member of sports team"
        },
        {
            "year": "2001",
            "template": "In the year the World Series was held in Arizona, {} was a member of sports team"
        },
        {
            "year": "2002",
            "template": "In the year the Winter Olympics were held in Salt Lake City, {} was a member of sports team"
        },
        {
            "year": "2003",
            "template": "In the year the Rugby World Cup was held in Australia, {} was a member of sports team"
        },
        {
            "year": "2004",
            "template": "In the year the Summer Olympics were held in Athens, {} was a member of sports team"
        },
        {
            "year": "2005",
            "template": "In the year the Champions League final was held in Istanbul, {} was a member of sports team"
        },
        {
            "year": "2006",
            "template": "In the year the FIFA World Cup was held in Germany, {} was a member of sports team"
        },
        {
            "year": "2007",
            "template": "In the year the Cricket World Cup was held in the West Indies, {} was a member of sports team"
        },
        {
            "year": "2008",
            "template": "In the year the Summer Olympics were held in Beijing, {} was a member of sports team"
        },
        {
            "year": "2009",
            "template": "In the year the Champions League final was held in Rome, {} was a member of sports team"
        },
        {
            "year": "2010",
            "template": "In the year the FIFA World Cup was held in South Africa, {} was a member of sports team"
        },
        {
            "year": "2011",
            "template": "In the year the Rugby World Cup was held in New Zealand, {} was a member of sports team"
        },
        {
            "year": "2012",
            "template": "In the year the Summer Olympics were held in London, {} was a member of sports team"
        },
        {
            "year": "2013",
            "template": "In the year the Confederations Cup was held in Brazil, {} was a member of sports team"
        },
        {
            "year": "2014",
            "template": "In the year the FIFA World Cup was held in Brazil, {} was a member of sports team"
        },
        {
            "year": "2015",
            "template": "In the year the Cricket World Cup was held in Australia, {} was a member of sports team"
        },
        {
            "year": "2016",
            "template": "In the year the Summer Olympics were held in Rio, {} was a member of sports team"
        },
        {
            "year": "2017",
            "template": "In the year the Champions League final was held in Cardiff, {} was a member of sports team"
        },
        {
            "year": "2018",
            "template": "In the year the FIFA World Cup was held in Russia, {} was a member of sports team"
        },
        {
            "year": "2019",
            "template": "In the year the Rugby World Cup was held in Japan, {} was a member of sports team"
        },
        {
            "year": "2020",
            "template": "In the year the Summer Olympics were postponed in Tokyo, {} was a member of sports team"
        }
    ],
    "all_possible_objects": [
        {
            "subject": "United States",
            "objects": [
                "2.19",
                "3.38",
                "2.83",
                "1.59",
                "2.27",
                "2.68",
                "3.39",
                "3.23",
                "2.85",
                "3.84",
                "-0.36"
            ],
            "year_range": "1999-2009"
        },
        {
            "subject": "Brazil",
            "objects": [
                "8.94",
                "6.00",
                "7.67",
                "8.44",
                "14.71",
                "6.60",
                "6.87",
                "3.14",
                "4.46",
                "5.90",
                "4.31"
            ],
            "year_range": "1999-2009"
        },
        {
            "subject": "South Korea",
            "objects": [
                "0.81",
                "2.28",
                "4.08",
                "2.75",
                "3.57",
                "3.63",
                "2.77",
                "2.22",
                "2.53",
                "4.67",
                "2.76"
            ],
            "year_range": "1999-2009"
        }
    ],
    "predictions": {
        "prompt_templates:0": [
            {
                "subject": "United States",
                "object": "2.19",
                "time": "1999",
                "probs": {
                    "2.19": 0.037874579429626465,
                    "3.38": 0.19410166144371033,
                    "2.83": 0.049245741218328476,
                    "1.59": 0.04374997317790985,
                    "2.27": 0.11654849350452423,
                    "2.68": 0.03632095456123352,
                    "3.39": 0.19840018451213837,
                    "3.23": 0.0270466897636652,
                    "2.85": 0.07070615142583847,
                    "3.84": 0.019073763862252235,
                    "-0.36": 0.2069317251443863
                }
            },
            {
                "subject": "United States",
                "object": "3.38",
                "time": "2000",
                "probs": {
                    "2.19": 0.03536359965801239,
                    "3.38": 0.22642427682876587,
                    "2.83": 0.044529154896736145,
                    "1.59": 0.06488104909658432,
                    "2.27": 0.11184810101985931,
                    "2.68": 0.043221086263656616,
                    "3.39": 0.2944175899028778,
                    "3.23": 0.029645277187228203,
                    "2.85": 0.0717688500881195,
                    "3.84": 0.014972462318837643,
                    "-0.36": 0.06292853504419327
                }
            },
            {
                "subject": "United States",
                "object": "2.83",
                "time": "2001",
                "probs": {
                    "2.19": 0.014768497087061405,
                    "3.38": 0.20840677618980408,
                    "2.83": 0.05148305371403694,
                    "1.59": 0.039114877581596375,
                    "2.27": 0.07149349898099899,
                    "2.68": 0.040469057857990265,
                    "3.39": 0.3236992061138153,
                    "3.23": 0.03449190780520439,
                    "2.85": 0.06484872102737427,
                    "3.84": 0.010402357205748558,
                    "-0.36": 0.14082209765911102
                }
            },
            {
                "subject": "United States",
                "object": "1.59",
                "time": "2002",
                "probs": {
                    "2.19": 0.01135232113301754,
                    "3.38": 0.2066861242055893,
                    "2.83": 0.03758925944566727,
                    "1.59": 0.02580120973289013,
                    "2.27": 0.042657624930143356,
                    "2.68": 0.04925338923931122,
                    "3.39": 0.2380177229642868,
                    "3.23": 0.03794453293085098,
                    "2.85": 0.05159604549407959,
                    "3.84": 0.009869315661489964,
                    "-0.36": 0.28923237323760986
                }
            },
            {
                "subject": "United States",
                "object": "2.27",
                "time": "2003",
                "probs": {
                    "2.19": 0.01128767803311348,
                    "3.38": 0.07795163244009018,
                    "2.83": 0.04923291876912117,
                    "1.59": 0.04722093790769577,
                    "2.27": 0.04896078631281853,
                    "2.68": 0.05514182895421982,
                    "3.39": 0.0759865790605545,
                    "3.23": 0.05281759798526764,
                    "2.85": 0.061196375638246536,
                    "3.84": 0.012803747318685055,
                    "-0.36": 0.5073999166488647
                }
            },
            {
                "subject": "United States",
                "object": "2.68",
                "time": "2004",
                "probs": {
                    "2.19": 0.015946457162499428,
                    "3.38": 0.20930632948875427,
                    "2.83": 0.07292668521404266,
                    "1.59": 0.060650765895843506,
                    "2.27": 0.04466361179947853,
                    "2.68": 0.04673177748918533,
                    "3.39": 0.1620086282491684,
                    "3.23": 0.05411931127309799,
                    "2.85": 0.08749549835920334,
                    "3.84": 0.02032150886952877,
                    "-0.36": 0.22582942247390747
                }
            },
            {
                "subject": "United States",
                "object": "3.39",
                "time": "2005",
                "probs": {
                    "2.19": 0.017203085124492645,
                    "3.38": 0.05940220504999161,
                    "2.83": 0.04108584672212601,
                    "1.59": 0.03743678703904152,
                    "2.27": 0.045853111892938614,
                    "2.68": 0.04413352906703949,
                    "3.39": 0.05428951978683472,
                    "3.23": 0.05380624160170555,
                    "2.85": 0.05251453071832657,
                    "3.84": 0.02113877795636654,
                    "-0.36": 0.5731363296508789
                }
            },
            {
                "subject": "United States",
                "object": "3.23",
                "time": "2006",
                "probs": {
                    "2.19": 0.008082708343863487,
                    "3.38": 0.018857276067137718,
                    "2.83": 0.09289385378360748,
                    "1.59": 0.06724824756383896,
                    "2.27": 0.02747970260679722,
                    "2.68": 0.03164680674672127,
                    "3.39": 0.021521395072340965,
                    "3.23": 0.19793878495693207,
                    "2.85": 0.08205237984657288,
                    "3.84": 0.010339400731027126,
                    "-0.36": 0.44193944334983826
                }
            },
            {
                "subject": "United States",
                "object": "2.85",
                "time": "2007",
                "probs": {
                    "2.19": 0.009759929962456226,
                    "3.38": 0.01637832261621952,
                    "2.83": 0.06578783690929413,
                    "1.59": 0.03824466094374657,
                    "2.27": 0.019693801179528236,
                    "2.68": 0.033543121069669724,
                    "3.39": 0.014168634079396725,
                    "3.23": 0.018196148797869682,
                    "2.85": 0.07114771753549576,
                    "3.84": 0.10240699350833893,
                    "-0.36": 0.6106728911399841
                }
            },
            {
                "subject": "United States",
                "object": "3.84",
                "time": "2008",
                "probs": {
                    "2.19": 0.008815986104309559,
                    "3.38": 0.00860339030623436,
                    "2.83": 0.03100174479186535,
                    "1.59": 0.060361120849847794,
                    "2.27": 0.02885076031088829,
                    "2.68": 0.07451272755861282,
                    "3.39": 0.007145806215703487,
                    "3.23": 0.00866914726793766,
                    "2.85": 0.04601851850748062,
                    "3.84": 0.28583046793937683,
                    "-0.36": 0.4401904046535492
                }
            },
            {
                "subject": "United States",
                "object": "-0.36",
                "time": "2009",
                "probs": {
                    "2.19": 0.008110281080007553,
                    "3.38": 0.002347717760130763,
                    "2.83": 0.010277418419718742,
                    "1.59": 0.0344543531537056,
                    "2.27": 0.024961421266198158,
                    "2.68": 0.0526917539536953,
                    "3.39": 0.0010180602548643947,
                    "3.23": 0.0018582392949610949,
                    "2.85": 0.016922958195209503,
                    "3.84": 0.08188032358884811,
                    "-0.36": 0.7654774188995361
                }
            },
            {
                "subject": "Brazil",
                "object": "8.94",
                "time": "1999",
                "probs": {
                    "8.94": 0.08386431634426117,
                    "6.00": 0.046177905052900314,
                    "7.67": 0.10881245136260986,
                    "8.44": 0.033270213752985,
                    "14.71": 0.42349717020988464,
                    "6.60": 0.023240886628627777,
                    "6.87": 0.06353974342346191,
                    "3.14": 0.03930656239390373,
                    "4.46": 0.054141294211149216,
                    "5.90": 0.06509346514940262,
                    "4.31": 0.05905590206384659
                }
            },
            {
                "subject": "Brazil",
                "object": "6.00",
                "time": "2000",
                "probs": {
                    "8.94": 0.056867994368076324,
                    "6.00": 0.11805875599384308,
                    "7.67": 0.07505415380001068,
                    "8.44": 0.023920761421322823,
                    "14.71": 0.30301275849342346,
                    "6.60": 0.039666954427957535,
                    "6.87": 0.0876735970377922,
                    "3.14": 0.09164869785308838,
                    "4.46": 0.05469754710793495,
                    "5.90": 0.0780940055847168,
                    "4.31": 0.07130477577447891
                }
            },
            {
                "subject": "Brazil",
                "object": "7.67",
                "time": "2001",
                "probs": {
                    "8.94": 0.08956949412822723,
                    "6.00": 0.09019695222377777,
                    "7.67": 0.049588534981012344,
                    "8.44": 0.02669331058859825,
                    "14.71": 0.2887040376663208,
                    "6.60": 0.03940413147211075,
                    "6.87": 0.06715050339698792,
                    "3.14": 0.10915831476449966,
                    "4.46": 0.06167956441640854,
                    "5.90": 0.07486666738986969,
                    "4.31": 0.10298851877450943
                }
            },
            {
                "subject": "Brazil",
                "object": "8.44",
                "time": "2002",
                "probs": {
                    "8.94": 0.05952351912856102,
                    "6.00": 0.09532354772090912,
                    "7.67": 0.05179509148001671,
                    "8.44": 0.028238600119948387,
                    "14.71": 0.3418150246143341,
                    "6.60": 0.06415755301713943,
                    "6.87": 0.0789283886551857,
                    "3.14": 0.06299468874931335,
                    "4.46": 0.06975296884775162,
                    "5.90": 0.08483493328094482,
                    "4.31": 0.06263573467731476
                }
            },
            {
                "subject": "Brazil",
                "object": "14.71",
                "time": "2003",
                "probs": {
                    "8.94": 0.07256896048784256,
                    "6.00": 0.12179886549711227,
                    "7.67": 0.05556249991059303,
                    "8.44": 0.03298153355717659,
                    "14.71": 0.2927716076374054,
                    "6.60": 0.038876574486494064,
                    "6.87": 0.05766620859503746,
                    "3.14": 0.08574393391609192,
                    "4.46": 0.06244295835494995,
                    "5.90": 0.08523325622081757,
                    "4.31": 0.09435360878705978
                }
            },
            {
                "subject": "Brazil",
                "object": "6.60",
                "time": "2004",
                "probs": {
                    "8.94": 0.051045529544353485,
                    "6.00": 0.11225847154855728,
                    "7.67": 0.039743684232234955,
                    "8.44": 0.025412533432245255,
                    "14.71": 0.437180757522583,
                    "6.60": 0.03836281970143318,
                    "6.87": 0.05962911620736122,
                    "3.14": 0.0768960639834404,
                    "4.46": 0.04910124093294144,
                    "5.90": 0.06016262248158455,
                    "4.31": 0.050207193940877914
                }
            },
            {
                "subject": "Brazil",
                "object": "6.87",
                "time": "2005",
                "probs": {
                    "8.94": 0.04956157132983208,
                    "6.00": 0.13746021687984467,
                    "7.67": 0.0370204895734787,
                    "8.44": 0.019887354224920273,
                    "14.71": 0.36344650387763977,
                    "6.60": 0.0376351922750473,
                    "6.87": 0.05041411891579628,
                    "3.14": 0.07556948810815811,
                    "4.46": 0.06191941723227501,
                    "5.90": 0.0888536274433136,
                    "4.31": 0.07823199033737183
                }
            },
            {
                "subject": "Brazil",
                "object": "3.14",
                "time": "2006",
                "probs": {
                    "8.94": 0.04623834043741226,
                    "6.00": 0.12399725615978241,
                    "7.67": 0.037297822535037994,
                    "8.44": 0.02481861598789692,
                    "14.71": 0.32506078481674194,
                    "6.60": 0.03634941950440407,
                    "6.87": 0.053191788494586945,
                    "3.14": 0.12731553614139557,
                    "4.46": 0.0677461251616478,
                    "5.90": 0.06222950294613838,
                    "4.31": 0.09575480222702026
                }
            },
            {
                "subject": "Brazil",
                "object": "4.46",
                "time": "2007",
                "probs": {
                    "8.94": 0.037871260195970535,
                    "6.00": 0.14221490919589996,
                    "7.67": 0.03910474106669426,
                    "8.44": 0.020525002852082253,
                    "14.71": 0.27021023631095886,
                    "6.60": 0.033035680651664734,
                    "6.87": 0.05860248580574989,
                    "3.14": 0.13677509129047394,
                    "4.46": 0.08363477885723114,
                    "5.90": 0.0749640092253685,
                    "4.31": 0.10306185483932495
                }
            },
            {
                "subject": "Brazil",
                "object": "5.90",
                "time": "2008",
                "probs": {
                    "8.94": 0.04198944941163063,
                    "6.00": 0.11000004410743713,
                    "7.67": 0.04287220537662506,
                    "8.44": 0.018176931887865067,
                    "14.71": 0.34140846133232117,
                    "6.60": 0.0381588377058506,
                    "6.87": 0.05383947864174843,
                    "3.14": 0.10936948657035828,
                    "4.46": 0.09435651451349258,
                    "5.90": 0.06041178107261658,
                    "4.31": 0.08941677212715149
                }
            },
            {
                "subject": "Brazil",
                "object": "4.31",
                "time": "2009",
                "probs": {
                    "8.94": 0.037125106900930405,
                    "6.00": 0.11731375008821487,
                    "7.67": 0.044904761016368866,
                    "8.44": 0.016777189448475838,
                    "14.71": 0.2595600187778473,
                    "6.60": 0.03772657737135887,
                    "6.87": 0.04224547743797302,
                    "3.14": 0.1508914828300476,
                    "4.46": 0.08684923499822617,
                    "5.90": 0.0967189371585846,
                    "4.31": 0.10988745093345642
                }
            },
            {
                "subject": "South Korea",
                "object": "0.81",
                "time": "1999",
                "probs": {
                    "0.81": 0.10856739431619644,
                    "2.28": 0.09986753016710281,
                    "4.08": 0.05862762778997421,
                    "2.75": 0.17459630966186523,
                    "3.57": 0.06816715747117996,
                    "3.63": 0.0573132298886776,
                    "2.77": 0.10589801520109177,
                    "2.22": 0.09986753016710281,
                    "2.53": 0.06344238668680191,
                    "4.67": 0.05775480717420578,
                    "2.76": 0.10589801520109177
                }
            },
            {
                "subject": "South Korea",
                "object": "2.28",
                "time": "2000",
                "probs": {
                    "0.81": 0.06869522482156754,
                    "2.28": 0.09820860624313354,
                    "4.08": 0.05910298228263855,
                    "2.75": 0.15996751189231873,
                    "3.57": 0.08280599862337112,
                    "3.63": 0.06541953980922699,
                    "2.77": 0.09702520072460175,
                    "2.22": 0.09820860624313354,
                    "2.53": 0.07036399096250534,
                    "4.67": 0.07561953365802765,
                    "2.76": 0.12458282709121704
                }
            },
            {
                "subject": "South Korea",
                "object": "4.08",
                "time": "2001",
                "probs": {
                    "0.81": 0.054230671375989914,
                    "2.28": 0.0932038202881813,
                    "4.08": 0.05942412093281746,
                    "2.75": 0.18875151872634888,
                    "3.57": 0.0743999034166336,
                    "3.63": 0.06594735383987427,
                    "2.77": 0.08915990591049194,
                    "2.22": 0.0932038202881813,
                    "2.53": 0.09960935264825821,
                    "4.67": 0.06758597493171692,
                    "2.76": 0.11448357999324799
                }
            },
            {
                "subject": "South Korea",
                "object": "2.75",
                "time": "2002",
                "probs": {
                    "0.81": 0.05318206548690796,
                    "2.28": 0.11856982856988907,
                    "4.08": 0.05346154794096947,
                    "2.75": 0.15273937582969666,
                    "3.57": 0.0731787234544754,
                    "3.63": 0.06578316539525986,
                    "2.77": 0.09264076501131058,
                    "2.22": 0.11856982856988907,
                    "2.53": 0.087831050157547,
                    "4.67": 0.06509047001600266,
                    "2.76": 0.11895310133695602
                }
            },
            {
                "subject": "South Korea",
                "object": "3.57",
                "time": "2003",
                "probs": {
                    "0.81": 0.08185411989688873,
                    "2.28": 0.10572325438261032,
                    "4.08": 0.0632355585694313,
                    "2.75": 0.13734053075313568,
                    "3.57": 0.07913323491811752,
                    "3.63": 0.07570760697126389,
                    "2.77": 0.08330092579126358,
                    "2.22": 0.10572325438261032,
                    "2.53": 0.09421460330486298,
                    "4.67": 0.0668063759803772,
                    "2.76": 0.10696051269769669
                }
            },
            {
                "subject": "South Korea",
                "object": "3.63",
                "time": "2004",
                "probs": {
                    "0.81": 0.07494569569826126,
                    "2.28": 0.08854914456605911,
                    "4.08": 0.06384625285863876,
                    "2.75": 0.15713615715503693,
                    "3.57": 0.07276133447885513,
                    "3.63": 0.08658472448587418,
                    "2.77": 0.09530789405107498,
                    "2.22": 0.08854914456605911,
                    "2.53": 0.08643589168787003,
                    "4.67": 0.06350594758987427,
                    "2.76": 0.12237776070833206
                }
            },
            {
                "subject": "South Korea",
                "object": "2.77",
                "time": "2005",
                "probs": {
                    "0.81": 0.07660029083490372,
                    "2.28": 0.09229331463575363,
                    "4.08": 0.059299468994140625,
                    "2.75": 0.15391500294208527,
                    "3.57": 0.07334668189287186,
                    "3.63": 0.0738813504576683,
                    "2.77": 0.09335417300462723,
                    "2.22": 0.09229331463575363,
                    "2.53": 0.09948044270277023,
                    "4.67": 0.06566682457923889,
                    "2.76": 0.11986912786960602
                }
            },
            {
                "subject": "South Korea",
                "object": "2.22",
                "time": "2006",
                "probs": {
                    "0.81": 0.07859183847904205,
                    "2.28": 0.11336667835712433,
                    "4.08": 0.051048487424850464,
                    "2.75": 0.14505904912948608,
                    "3.57": 0.06713654100894928,
                    "3.63": 0.06840899586677551,
                    "2.77": 0.11297210305929184,
                    "2.22": 0.11336667835712433,
                    "2.53": 0.08431286364793777,
                    "4.67": 0.052764661610126495,
                    "2.76": 0.11297210305929184
                }
            },
            {
                "subject": "South Korea",
                "object": "2.53",
                "time": "2007",
                "probs": {
                    "0.81": 0.08674095571041107,
                    "2.28": 0.09412911534309387,
                    "4.08": 0.057692065834999084,
                    "2.75": 0.1720101684331894,
                    "3.57": 0.08208271861076355,
                    "3.63": 0.06499522179365158,
                    "2.77": 0.10432944446802139,
                    "2.22": 0.09412911534309387,
                    "2.53": 0.07622691243886948,
                    "4.67": 0.06333479285240173,
                    "2.76": 0.10432944446802139
                }
            },
            {
                "subject": "South Korea",
                "object": "4.67",
                "time": "2008",
                "probs": {
                    "0.81": 0.08317896723747253,
                    "2.28": 0.11811117082834244,
                    "4.08": 0.06720869243144989,
                    "2.75": 0.1372724026441574,
                    "3.57": 0.05925040692090988,
                    "3.63": 0.07067418098449707,
                    "2.77": 0.08325992524623871,
                    "2.22": 0.11811117082834244,
                    "2.53": 0.09394936263561249,
                    "4.67": 0.0620758943259716,
                    "2.76": 0.10690785944461823
                }
            },
            {
                "subject": "South Korea",
                "object": "2.76",
                "time": "2009",
                "probs": {
                    "0.81": 0.1184261292219162,
                    "2.28": 0.0998176634311676,
                    "4.08": 0.054091762751340866,
                    "2.75": 0.13945706188678741,
                    "3.57": 0.07019005715847015,
                    "3.63": 0.07284397631883621,
                    "2.77": 0.10860927402973175,
                    "2.22": 0.0998176634311676,
                    "2.53": 0.06997992098331451,
                    "4.67": 0.05815719813108444,
                    "2.76": 0.10860927402973175
                }
            }
        ],
        "prompt_templates_zs:0": [
            {
                "subject": "United States",
                "object": "2.19",
                "time": "1999",
                "probs": {
                    "2.19": 0.001018947921693325,
                    "3.38": 0.6380534768104553,
                    "2.83": 0.017585644498467445,
                    "1.59": 0.009055215865373611,
                    "2.27": 0.01853422448039055,
                    "2.68": 0.004510926548391581,
                    "3.39": 0.2998584508895874,
                    "3.23": 0.0006614151643589139,
                    "2.85": 0.010649239644408226,
                    "3.84": 5.4104533774079755e-05,
                    "-0.36": 1.8428094335831702e-05
                }
            },
            {
                "subject": "United States",
                "object": "3.38",
                "time": "2000",
                "probs": {
                    "2.19": 1.3476736967277247e-05,
                    "3.38": 0.5371886491775513,
                    "2.83": 0.00039175021811388433,
                    "1.59": 6.437462616304401e-06,
                    "2.27": 0.0005089776823297143,
                    "2.68": 9.03954278328456e-05,
                    "3.39": 0.4613223969936371,
                    "3.23": 0.00013846054207533598,
                    "2.85": 0.0003057524736505002,
                    "3.84": 2.374570794927422e-05,
                    "-0.36": 9.916446288116276e-06
                }
            },
            {
                "subject": "United States",
                "object": "2.83",
                "time": "2001",
                "probs": {
                    "2.19": 0.001285514677874744,
                    "3.38": 0.14464698731899261,
                    "2.83": 0.4383087158203125,
                    "1.59": 0.024736743420362473,
                    "2.27": 0.01643127016723156,
                    "2.68": 0.012775810435414314,
                    "3.39": 0.18569216132164001,
                    "3.23": 5.862410762347281e-05,
                    "2.85": 0.17599231004714966,
                    "3.84": 2.2079051632317714e-05,
                    "-0.36": 4.975249248673208e-05
                }
            },
            {
                "subject": "United States",
                "object": "1.59",
                "time": "2002",
                "probs": {
                    "2.19": 0.00027306549600325525,
                    "3.38": 0.05612828955054283,
                    "2.83": 0.398639976978302,
                    "1.59": 0.1933116763830185,
                    "2.27": 0.01841280609369278,
                    "2.68": 0.03261593356728554,
                    "3.39": 0.05634796991944313,
                    "3.23": 6.39741265331395e-05,
                    "2.85": 0.24412474036216736,
                    "3.84": 3.495931377983652e-05,
                    "-0.36": 4.6624845708720386e-05
                }
            },
            {
                "subject": "United States",
                "object": "2.27",
                "time": "2003",
                "probs": {
                    "2.19": 0.0030432515777647495,
                    "3.38": 0.03517746552824974,
                    "2.83": 0.46493396162986755,
                    "1.59": 0.008904578164219856,
                    "2.27": 0.06590292602777481,
                    "2.68": 0.15062560141086578,
                    "3.39": 0.049965232610702515,
                    "3.23": 0.0003735231002792716,
                    "2.85": 0.2206353098154068,
                    "3.84": 4.513751628110185e-05,
                    "-0.36": 0.0003930048842448741
                }
            },
            {
                "subject": "United States",
                "object": "2.68",
                "time": "2004",
                "probs": {
                    "2.19": 0.0003726989671122283,
                    "3.38": 0.21671393513679504,
                    "2.83": 0.42334169149398804,
                    "1.59": 3.384114825166762e-05,
                    "2.27": 0.007468915544450283,
                    "2.68": 0.01872735098004341,
                    "3.39": 0.13074451684951782,
                    "3.23": 0.0009854432428255677,
                    "2.85": 0.20154087245464325,
                    "3.84": 2.1397312593762763e-05,
                    "-0.36": 4.937739504384808e-05
                }
            },
            {
                "subject": "United States",
                "object": "3.39",
                "time": "2005",
                "probs": {
                    "2.19": 2.1770311775526352e-07,
                    "3.38": 0.4849243760108948,
                    "2.83": 0.003857929725199938,
                    "1.59": 3.3865360364870867e-06,
                    "2.27": 1.0911042409134097e-05,
                    "2.68": 0.0006054918630979955,
                    "3.39": 0.48120570182800293,
                    "3.23": 0.02548041008412838,
                    "2.85": 0.003870252752676606,
                    "3.84": 3.833046503132209e-05,
                    "-0.36": 2.9591351449198555e-06
                }
            },
            {
                "subject": "United States",
                "object": "3.23",
                "time": "2006",
                "probs": {
                    "2.19": 1.0948355111395358e-06,
                    "3.38": 0.07809099555015564,
                    "2.83": 0.059751685708761215,
                    "1.59": 8.015925413928926e-05,
                    "2.27": 2.9752442060271278e-05,
                    "2.68": 0.002178581664338708,
                    "3.39": 0.06006065383553505,
                    "3.23": 0.7599538564682007,
                    "2.85": 0.039452798664569855,
                    "3.84": 0.0002829992154147476,
                    "-0.36": 0.00011740327317966148
                }
            },
            {
                "subject": "United States",
                "object": "2.85",
                "time": "2007",
                "probs": {
                    "2.19": 1.3736638720729388e-05,
                    "3.38": 0.0036438116803765297,
                    "2.83": 0.3548344075679779,
                    "1.59": 3.246190681238659e-05,
                    "2.27": 3.828947228612378e-05,
                    "2.68": 0.0006015676190145314,
                    "3.39": 0.006496837828308344,
                    "3.23": 0.001632388331927359,
                    "2.85": 0.5969030261039734,
                    "3.84": 0.03569507598876953,
                    "-0.36": 0.0001083574170479551
                }
            },
            {
                "subject": "United States",
                "object": "3.84",
                "time": "2008",
                "probs": {
                    "2.19": 0.00014849251601845026,
                    "3.38": 0.002527746604755521,
                    "2.83": 0.08859637379646301,
                    "1.59": 0.0025674940552562475,
                    "2.27": 0.001370940008200705,
                    "2.68": 0.0054814014583826065,
                    "3.39": 0.005342224612832069,
                    "3.23": 8.074507059063762e-05,
                    "2.85": 0.09832046926021576,
                    "3.84": 0.7945216298103333,
                    "-0.36": 0.0010424788342788815
                }
            },
            {
                "subject": "United States",
                "object": "-0.36",
                "time": "2009",
                "probs": {
                    "2.19": 0.0029422028455883265,
                    "3.38": 0.0011778698535636067,
                    "2.83": 0.07237686961889267,
                    "1.59": 6.688626308459789e-05,
                    "2.27": 0.10624060779809952,
                    "2.68": 0.6524233222007751,
                    "3.39": 0.0012839124538004398,
                    "3.23": 8.965167216956615e-05,
                    "2.85": 0.09405075013637543,
                    "3.84": 0.054173875600099564,
                    "-0.36": 0.01517402846366167
                }
            },
            {
                "subject": "Brazil",
                "object": "8.94",
                "time": "1999",
                "probs": {
                    "8.94": 0.004795139189809561,
                    "6.00": 0.0004928908892907202,
                    "7.67": 0.00118971336632967,
                    "8.44": 0.0010587021242827177,
                    "14.71": 0.9844027757644653,
                    "6.60": 0.0007591760368086398,
                    "6.87": 0.0030096631962805986,
                    "3.14": 0.0014200707664713264,
                    "4.46": 0.001091317622922361,
                    "5.90": 0.00090099370572716,
                    "4.31": 0.0008795181638561189
                }
            },
            {
                "subject": "Brazil",
                "object": "6.00",
                "time": "2000",
                "probs": {
                    "8.94": 0.0026799801271408796,
                    "6.00": 0.0005038338713347912,
                    "7.67": 0.003041986608877778,
                    "8.44": 0.000902363914065063,
                    "14.71": 0.9861932396888733,
                    "6.60": 0.0003017517738044262,
                    "6.87": 0.002200828166678548,
                    "3.14": 0.001123198657296598,
                    "4.46": 0.0009388829348608851,
                    "5.90": 0.0009290638845413923,
                    "4.31": 0.0011847964487969875
                }
            },
            {
                "subject": "Brazil",
                "object": "7.67",
                "time": "2001",
                "probs": {
                    "8.94": 0.001662100083194673,
                    "6.00": 0.0010322812013328075,
                    "7.67": 0.005921183153986931,
                    "8.44": 0.0013259407132863998,
                    "14.71": 0.9826280474662781,
                    "6.60": 0.0006685227854177356,
                    "6.87": 0.0028957007452845573,
                    "3.14": 0.0009550100658088923,
                    "4.46": 0.0013866085791960359,
                    "5.90": 0.000718003255315125,
                    "4.31": 0.0008066201698966324
                }
            },
            {
                "subject": "Brazil",
                "object": "8.44",
                "time": "2002",
                "probs": {
                    "8.94": 0.0037732624914497137,
                    "6.00": 0.003071528160944581,
                    "7.67": 0.012464521452784538,
                    "8.44": 0.0031805343460291624,
                    "14.71": 0.9368754029273987,
                    "6.60": 0.002456995192915201,
                    "6.87": 0.009157514199614525,
                    "3.14": 0.004840789828449488,
                    "4.46": 0.008678433485329151,
                    "5.90": 0.0033756792545318604,
                    "4.31": 0.012125351466238499
                }
            },
            {
                "subject": "Brazil",
                "object": "14.71",
                "time": "2003",
                "probs": {
                    "8.94": 0.0071331048384308815,
                    "6.00": 0.005656241439282894,
                    "7.67": 0.011556638404726982,
                    "8.44": 0.004241730086505413,
                    "14.71": 0.917280375957489,
                    "6.60": 0.0024653796572238207,
                    "6.87": 0.008426617830991745,
                    "3.14": 0.0063459607772529125,
                    "4.46": 0.010928758420050144,
                    "5.90": 0.007641386240720749,
                    "4.31": 0.018323881551623344
                }
            },
            {
                "subject": "Brazil",
                "object": "6.60",
                "time": "2004",
                "probs": {
                    "8.94": 0.008309911005198956,
                    "6.00": 0.021549994125962257,
                    "7.67": 0.01619422622025013,
                    "8.44": 0.0054316334426403046,
                    "14.71": 0.668133556842804,
                    "6.60": 0.00928106252104044,
                    "6.87": 0.030460001900792122,
                    "3.14": 0.019605930894613266,
                    "4.46": 0.0895911455154419,
                    "5.90": 0.03157181665301323,
                    "4.31": 0.0998706966638565
                }
            },
            {
                "subject": "Brazil",
                "object": "6.87",
                "time": "2005",
                "probs": {
                    "8.94": 0.013450921513140202,
                    "6.00": 0.017880722880363464,
                    "7.67": 0.00920898374170065,
                    "8.44": 0.006294803228229284,
                    "14.71": 0.7767539620399475,
                    "6.60": 0.0077919261530041695,
                    "6.87": 0.028149861842393875,
                    "3.14": 0.01147362682968378,
                    "4.46": 0.058704275637865067,
                    "5.90": 0.02280445583164692,
                    "4.31": 0.04748652130365372
                }
            },
            {
                "subject": "Brazil",
                "object": "3.14",
                "time": "2006",
                "probs": {
                    "8.94": 0.027886465191841125,
                    "6.00": 0.03550389036536217,
                    "7.67": 0.010553544387221336,
                    "8.44": 0.010700944811105728,
                    "14.71": 0.6899152994155884,
                    "6.60": 0.008355040103197098,
                    "6.87": 0.05157003924250603,
                    "3.14": 0.015417061746120453,
                    "4.46": 0.05565638467669487,
                    "5.90": 0.03353167697787285,
                    "4.31": 0.060909636318683624
                }
            },
            {
                "subject": "Brazil",
                "object": "4.46",
                "time": "2007",
                "probs": {
                    "8.94": 0.047246526926755905,
                    "6.00": 0.03521768003702164,
                    "7.67": 0.008933820761740208,
                    "8.44": 0.008992218412458897,
                    "14.71": 0.7494452595710754,
                    "6.60": 0.007246982306241989,
                    "6.87": 0.018120072782039642,
                    "3.14": 0.009487971663475037,
                    "4.46": 0.03298414871096611,
                    "5.90": 0.05796145275235176,
                    "4.31": 0.024363884702324867
                }
            },
            {
                "subject": "Brazil",
                "object": "5.90",
                "time": "2008",
                "probs": {
                    "8.94": 0.06412532180547714,
                    "6.00": 0.0406075082719326,
                    "7.67": 0.006730252876877785,
                    "8.44": 0.003348330967128277,
                    "14.71": 0.8118118047714233,
                    "6.60": 0.009284905157983303,
                    "6.87": 0.016341080889105797,
                    "3.14": 0.0018796769436448812,
                    "4.46": 0.009087205864489079,
                    "5.90": 0.032160211354494095,
                    "4.31": 0.004623689688742161
                }
            },
            {
                "subject": "Brazil",
                "object": "4.31",
                "time": "2009",
                "probs": {
                    "8.94": 0.034149445593357086,
                    "6.00": 0.11775611340999603,
                    "7.67": 0.01417004968971014,
                    "8.44": 0.0035369861871004105,
                    "14.71": 0.5858132243156433,
                    "6.60": 0.016469305381178856,
                    "6.87": 0.0096922991797328,
                    "3.14": 0.01037913840264082,
                    "4.46": 0.05477087199687958,
                    "5.90": 0.08913212269544601,
                    "4.31": 0.06413043290376663
                }
            },
            {
                "subject": "South Korea",
                "object": "0.81",
                "time": "1999",
                "probs": {
                    "0.81": 0.024333279579877853,
                    "2.28": 0.05842374265193939,
                    "4.08": 0.1031653955578804,
                    "2.75": 0.16285516321659088,
                    "3.57": 0.17040792107582092,
                    "3.63": 0.08427955955266953,
                    "2.77": 0.09673762321472168,
                    "2.22": 0.04814319685101509,
                    "2.53": 0.11742642521858215,
                    "4.67": 0.027661502361297607,
                    "2.76": 0.1065661683678627
                }
            },
            {
                "subject": "South Korea",
                "object": "2.28",
                "time": "2000",
                "probs": {
                    "0.81": 0.009905293583869934,
                    "2.28": 0.043772611767053604,
                    "4.08": 0.07413945347070694,
                    "2.75": 0.15423601865768433,
                    "3.57": 0.18834061920642853,
                    "3.63": 0.17508326470851898,
                    "2.77": 0.0771716833114624,
                    "2.22": 0.03335485979914665,
                    "2.53": 0.0961516797542572,
                    "4.67": 0.018719661980867386,
                    "2.76": 0.12912490963935852
                }
            },
            {
                "subject": "South Korea",
                "object": "4.08",
                "time": "2001",
                "probs": {
                    "0.81": 0.01669062301516533,
                    "2.28": 0.04660617560148239,
                    "4.08": 0.10240171104669571,
                    "2.75": 0.12197299301624298,
                    "3.57": 0.22146186232566833,
                    "3.63": 0.15087875723838806,
                    "2.77": 0.06655683368444443,
                    "2.22": 0.0381050743162632,
                    "2.53": 0.11002036184072495,
                    "4.67": 0.039095114916563034,
                    "2.76": 0.08621049672365189
                }
            },
            {
                "subject": "South Korea",
                "object": "2.75",
                "time": "2002",
                "probs": {
                    "0.81": 0.016745075583457947,
                    "2.28": 0.04191892221570015,
                    "4.08": 0.11618510633707047,
                    "2.75": 0.14864157140254974,
                    "3.57": 0.21126386523246765,
                    "3.63": 0.12316332012414932,
                    "2.77": 0.08187438547611237,
                    "2.22": 0.03427907079458237,
                    "2.53": 0.09239580482244492,
                    "4.67": 0.034951161593198776,
                    "2.76": 0.0985817015171051
                }
            },
            {
                "subject": "South Korea",
                "object": "3.57",
                "time": "2003",
                "probs": {
                    "0.81": 0.017410412430763245,
                    "2.28": 0.03492134064435959,
                    "4.08": 0.12454966455698013,
                    "2.75": 0.12524336576461792,
                    "3.57": 0.22560948133468628,
                    "3.63": 0.1667555421590805,
                    "2.77": 0.06284672766923904,
                    "2.22": 0.028708860278129578,
                    "2.53": 0.06530340760946274,
                    "4.67": 0.05366140604019165,
                    "2.76": 0.09498979896306992
                }
            },
            {
                "subject": "South Korea",
                "object": "3.63",
                "time": "2004",
                "probs": {
                    "0.81": 0.011535461992025375,
                    "2.28": 0.04071681946516037,
                    "4.08": 0.18429477512836456,
                    "2.75": 0.10360740125179291,
                    "3.57": 0.22632873058319092,
                    "3.63": 0.12916302680969238,
                    "2.77": 0.05233170837163925,
                    "2.22": 0.02611842192709446,
                    "2.53": 0.05093219876289368,
                    "4.67": 0.08781850337982178,
                    "2.76": 0.08715303987264633
                }
            },
            {
                "subject": "South Korea",
                "object": "2.77",
                "time": "2005",
                "probs": {
                    "0.81": 0.014387181960046291,
                    "2.28": 0.028380136936903,
                    "4.08": 0.2717687487602234,
                    "2.75": 0.09282372891902924,
                    "3.57": 0.2405552715063095,
                    "3.63": 0.11881669610738754,
                    "2.77": 0.030987383797764778,
                    "2.22": 0.01855883188545704,
                    "2.53": 0.02852644957602024,
                    "4.67": 0.10374846309423447,
                    "2.76": 0.051447056233882904
                }
            },
            {
                "subject": "South Korea",
                "object": "2.22",
                "time": "2006",
                "probs": {
                    "0.81": 0.014849087223410606,
                    "2.28": 0.02166752703487873,
                    "4.08": 0.3627868592739105,
                    "2.75": 0.04357103258371353,
                    "3.57": 0.22885045409202576,
                    "3.63": 0.12925007939338684,
                    "2.77": 0.023711400106549263,
                    "2.22": 0.013650740496814251,
                    "2.53": 0.03484562784433365,
                    "4.67": 0.09028894454240799,
                    "2.76": 0.03652821481227875
                }
            },
            {
                "subject": "South Korea",
                "object": "2.53",
                "time": "2007",
                "probs": {
                    "0.81": 0.026657182723283768,
                    "2.28": 0.01836317963898182,
                    "4.08": 0.32152387499809265,
                    "2.75": 0.051178839057683945,
                    "3.57": 0.2125791609287262,
                    "3.63": 0.16091801226139069,
                    "2.77": 0.0205244030803442,
                    "2.22": 0.014992393553256989,
                    "2.53": 0.023449979722499847,
                    "4.67": 0.11583064496517181,
                    "2.76": 0.033982351422309875
                }
            },
            {
                "subject": "South Korea",
                "object": "4.67",
                "time": "2008",
                "probs": {
                    "0.81": 0.01880594901740551,
                    "2.28": 0.042414791882038116,
                    "4.08": 0.35392025113105774,
                    "2.75": 0.07886912673711777,
                    "3.57": 0.13182120025157928,
                    "3.63": 0.10945801436901093,
                    "2.77": 0.03654487431049347,
                    "2.22": 0.03478022664785385,
                    "2.53": 0.045504432171583176,
                    "4.67": 0.09683099389076233,
                    "2.76": 0.051050104200839996
                }
            },
            {
                "subject": "South Korea",
                "object": "2.76",
                "time": "2009",
                "probs": {
                    "0.81": 0.021029667928814888,
                    "2.28": 0.029011836275458336,
                    "4.08": 0.3948347866535187,
                    "2.75": 0.057644568383693695,
                    "3.57": 0.09635474532842636,
                    "3.63": 0.17105814814567566,
                    "2.77": 0.04401087388396263,
                    "2.22": 0.02388926036655903,
                    "2.53": 0.02681417018175125,
                    "4.67": 0.09110372513532639,
                    "2.76": 0.04424823075532913
                }
            }
        ],
        "prompt_templates_zs:1": [
            {
                "subject": "United States",
                "object": "2.19",
                "time": "1999",
                "probs": {
                    "2.19": 0.01862463727593422,
                    "3.38": 0.2899192273616791,
                    "2.83": 0.23251807689666748,
                    "1.59": 0.011995463632047176,
                    "2.27": 0.09821277111768723,
                    "2.68": 0.0663350522518158,
                    "3.39": 0.13577981293201447,
                    "3.23": 0.0026839112397283316,
                    "2.85": 0.1421050876379013,
                    "3.84": 0.0014442539541050792,
                    "-0.36": 0.0003817706019617617
                }
            },
            {
                "subject": "United States",
                "object": "3.38",
                "time": "2000",
                "probs": {
                    "2.19": 0.00022451832774095237,
                    "3.38": 0.5265153050422668,
                    "2.83": 0.009608432650566101,
                    "1.59": 0.0001333092077402398,
                    "2.27": 0.002086325315758586,
                    "2.68": 0.0012320957612246275,
                    "3.39": 0.45597749948501587,
                    "3.23": 9.127453085966408e-05,
                    "2.85": 0.003994404803961515,
                    "3.84": 8.380424696952105e-05,
                    "-0.36": 5.306761522660963e-05
                }
            },
            {
                "subject": "United States",
                "object": "2.83",
                "time": "2001",
                "probs": {
                    "2.19": 0.0007333674002438784,
                    "3.38": 0.016140101477503777,
                    "2.83": 0.4484582543373108,
                    "1.59": 0.3324938118457794,
                    "2.27": 0.003986019641160965,
                    "2.68": 0.006610051728785038,
                    "3.39": 0.02644699066877365,
                    "3.23": 1.0344811016693711e-05,
                    "2.85": 0.16459639370441437,
                    "3.84": 1.579984927957412e-05,
                    "-0.36": 0.0005088576581329107
                }
            },
            {
                "subject": "United States",
                "object": "1.59",
                "time": "2002",
                "probs": {
                    "2.19": 0.00036592312972061336,
                    "3.38": 0.016904573887586594,
                    "2.83": 0.3993653655052185,
                    "1.59": 0.3114321231842041,
                    "2.27": 0.0018900538561865687,
                    "2.68": 0.011795444414019585,
                    "3.39": 0.014763905666768551,
                    "3.23": 1.401901499775704e-05,
                    "2.85": 0.24303442239761353,
                    "3.84": 1.8048212950816378e-05,
                    "-0.36": 0.00041612519999034703
                }
            },
            {
                "subject": "United States",
                "object": "2.27",
                "time": "2003",
                "probs": {
                    "2.19": 0.01909041777253151,
                    "3.38": 0.0043283128179609776,
                    "2.83": 0.5777915120124817,
                    "1.59": 0.014209217391908169,
                    "2.27": 0.05994182452559471,
                    "2.68": 0.04346233233809471,
                    "3.39": 0.006212996318936348,
                    "3.23": 0.00022727040050085634,
                    "2.85": 0.27352556586265564,
                    "3.84": 8.902142144506797e-05,
                    "-0.36": 0.0011214070254936814
                }
            },
            {
                "subject": "United States",
                "object": "2.68",
                "time": "2004",
                "probs": {
                    "2.19": 0.0007952179876156151,
                    "3.38": 0.09230048954486847,
                    "2.83": 0.5225231051445007,
                    "1.59": 0.0006788587779738009,
                    "2.27": 0.024512864649295807,
                    "2.68": 0.007622811943292618,
                    "3.39": 0.1034008339047432,
                    "3.23": 0.0003814100055024028,
                    "2.85": 0.24764105677604675,
                    "3.84": 1.9331491785123944e-05,
                    "-0.36": 0.00012408294423948973
                }
            },
            {
                "subject": "United States",
                "object": "3.39",
                "time": "2005",
                "probs": {
                    "2.19": 3.524960590084447e-08,
                    "3.38": 0.3153323531150818,
                    "2.83": 0.05692073702812195,
                    "1.59": 9.9565102118504e-07,
                    "2.27": 4.6990695068416244e-07,
                    "2.68": 0.00039023198769427836,
                    "3.39": 0.5834957361221313,
                    "3.23": 0.009068429470062256,
                    "2.85": 0.03476841375231743,
                    "3.84": 7.540182650700444e-06,
                    "-0.36": 1.5085981431184337e-05
                }
            },
            {
                "subject": "United States",
                "object": "3.23",
                "time": "2006",
                "probs": {
                    "2.19": 1.9655850280742015e-07,
                    "3.38": 0.0460624136030674,
                    "2.83": 0.07778181880712509,
                    "1.59": 1.662162867432926e-05,
                    "2.27": 8.670847364555812e-07,
                    "2.68": 0.0006996662705205381,
                    "3.39": 0.046150706708431244,
                    "3.23": 0.797111988067627,
                    "2.85": 0.03205191344022751,
                    "3.84": 4.5269222027854994e-05,
                    "-0.36": 7.855070725781843e-05
                }
            },
            {
                "subject": "United States",
                "object": "2.85",
                "time": "2007",
                "probs": {
                    "2.19": 9.88106990007509e-07,
                    "3.38": 0.013344529084861279,
                    "2.83": 0.4438800811767578,
                    "1.59": 1.8514652765588835e-05,
                    "2.27": 3.3038543278962607e-06,
                    "2.68": 0.00024769495939835906,
                    "3.39": 0.021819867193698883,
                    "3.23": 0.1825186014175415,
                    "2.85": 0.3014530837535858,
                    "3.84": 0.03663184121251106,
                    "-0.36": 8.154662646120414e-05
                }
            },
            {
                "subject": "United States",
                "object": "3.84",
                "time": "2008",
                "probs": {
                    "2.19": 0.0002807352284435183,
                    "3.38": 0.002184526761993766,
                    "2.83": 0.1118219643831253,
                    "1.59": 0.0015659111086279154,
                    "2.27": 0.001053663669154048,
                    "2.68": 0.0073541621677577496,
                    "3.39": 0.005928834900259972,
                    "3.23": 0.0003244359977543354,
                    "2.85": 0.12472929060459137,
                    "3.84": 0.7417166829109192,
                    "-0.36": 0.0030397491063922644
                }
            },
            {
                "subject": "United States",
                "object": "-0.36",
                "time": "2009",
                "probs": {
                    "2.19": 0.002740997588261962,
                    "3.38": 0.003104985924437642,
                    "2.83": 0.33971014618873596,
                    "1.59": 0.004573213867843151,
                    "2.27": 0.02577514946460724,
                    "2.68": 0.13229858875274658,
                    "3.39": 0.0027483475860208273,
                    "3.23": 0.0006207520491443574,
                    "2.85": 0.4435153603553772,
                    "3.84": 0.03982672095298767,
                    "-0.36": 0.005085660610347986
                }
            },
            {
                "subject": "Brazil",
                "object": "8.94",
                "time": "1999",
                "probs": {
                    "8.94": 0.002088255947455764,
                    "6.00": 0.00036719563649967313,
                    "7.67": 0.0005323541117832065,
                    "8.44": 0.0006088076625019312,
                    "14.71": 0.9872255921363831,
                    "6.60": 0.0008973874500952661,
                    "6.87": 0.002797349588945508,
                    "3.14": 0.0017137208487838507,
                    "4.46": 0.0010015357984229922,
                    "5.90": 0.001236948766745627,
                    "4.31": 0.0015309161972254515
                }
            },
            {
                "subject": "Brazil",
                "object": "6.00",
                "time": "2000",
                "probs": {
                    "8.94": 0.0005262634949758649,
                    "6.00": 0.00033961801091209054,
                    "7.67": 0.0004770709201693535,
                    "8.44": 0.00028874725103378296,
                    "14.71": 0.9930782914161682,
                    "6.60": 0.00035905308322981,
                    "6.87": 0.0009511097450740635,
                    "3.14": 0.0024773268960416317,
                    "4.46": 0.0005060987896285951,
                    "5.90": 0.0005272440612316132,
                    "4.31": 0.00046916608698666096
                }
            },
            {
                "subject": "Brazil",
                "object": "7.67",
                "time": "2001",
                "probs": {
                    "8.94": 0.001638233894482255,
                    "6.00": 0.001672968384809792,
                    "7.67": 0.005798435304313898,
                    "8.44": 0.0015905831241980195,
                    "14.71": 0.9728878736495972,
                    "6.60": 0.001988655421882868,
                    "6.87": 0.004951233975589275,
                    "3.14": 0.0029396475292742252,
                    "4.46": 0.0023678832221776247,
                    "5.90": 0.0018573255511000752,
                    "4.31": 0.0023071623872965574
                }
            },
            {
                "subject": "Brazil",
                "object": "8.44",
                "time": "2002",
                "probs": {
                    "8.94": 0.0013172263279557228,
                    "6.00": 0.0007420776528306305,
                    "7.67": 0.0015382557176053524,
                    "8.44": 0.0013165130512788892,
                    "14.71": 0.9828585386276245,
                    "6.60": 0.0008165813633240759,
                    "6.87": 0.004050631541758776,
                    "3.14": 0.0022454007994383574,
                    "4.46": 0.0014746948145329952,
                    "5.90": 0.0016635303618386388,
                    "4.31": 0.0019764560274779797
                }
            },
            {
                "subject": "Brazil",
                "object": "14.71",
                "time": "2003",
                "probs": {
                    "8.94": 0.004181545693427324,
                    "6.00": 0.010017928667366505,
                    "7.67": 0.008794170804321766,
                    "8.44": 0.003476608544588089,
                    "14.71": 0.8567947149276733,
                    "6.60": 0.00804932415485382,
                    "6.87": 0.01665685698390007,
                    "3.14": 0.024926811456680298,
                    "4.46": 0.02727542445063591,
                    "5.90": 0.015192531049251556,
                    "4.31": 0.02463415078818798
                }
            },
            {
                "subject": "Brazil",
                "object": "6.60",
                "time": "2004",
                "probs": {
                    "8.94": 0.004552789032459259,
                    "6.00": 0.010767600499093533,
                    "7.67": 0.010005238465964794,
                    "8.44": 0.00473942793905735,
                    "14.71": 0.7768411636352539,
                    "6.60": 0.01111516635864973,
                    "6.87": 0.01904725469648838,
                    "3.14": 0.01646604761481285,
                    "4.46": 0.05247732251882553,
                    "5.90": 0.024557936936616898,
                    "4.31": 0.06942998617887497
                }
            },
            {
                "subject": "Brazil",
                "object": "6.87",
                "time": "2005",
                "probs": {
                    "8.94": 0.01235946174710989,
                    "6.00": 0.009588031098246574,
                    "7.67": 0.00477620679885149,
                    "8.44": 0.007553803268820047,
                    "14.71": 0.7553523182868958,
                    "6.60": 0.011502017267048359,
                    "6.87": 0.022119693458080292,
                    "3.14": 0.013955825939774513,
                    "4.46": 0.0753558874130249,
                    "5.90": 0.020958809182047844,
                    "4.31": 0.06647800654172897
                }
            },
            {
                "subject": "Brazil",
                "object": "3.14",
                "time": "2006",
                "probs": {
                    "8.94": 0.024624696001410484,
                    "6.00": 0.015463917516171932,
                    "7.67": 0.007874971255660057,
                    "8.44": 0.00912238098680973,
                    "14.71": 0.6785600781440735,
                    "6.60": 0.01588919758796692,
                    "6.87": 0.04637465253472328,
                    "3.14": 0.011570898815989494,
                    "4.46": 0.08143974840641022,
                    "5.90": 0.0418149009346962,
                    "4.31": 0.06726450473070145
                }
            },
            {
                "subject": "Brazil",
                "object": "4.46",
                "time": "2007",
                "probs": {
                    "8.94": 0.03189742937684059,
                    "6.00": 0.03044091910123825,
                    "7.67": 0.007867777720093727,
                    "8.44": 0.019347356632351875,
                    "14.71": 0.5960477590560913,
                    "6.60": 0.04464546591043472,
                    "6.87": 0.04071658477187157,
                    "3.14": 0.006251383572816849,
                    "4.46": 0.06896490603685379,
                    "5.90": 0.09058006852865219,
                    "4.31": 0.06324038654565811
                }
            },
            {
                "subject": "Brazil",
                "object": "5.90",
                "time": "2008",
                "probs": {
                    "8.94": 0.07612690329551697,
                    "6.00": 0.010354033671319485,
                    "7.67": 0.0072004846297204494,
                    "8.44": 0.004478085786104202,
                    "14.71": 0.822221577167511,
                    "6.60": 0.01881120167672634,
                    "6.87": 0.01346079632639885,
                    "3.14": 0.0016769935609772801,
                    "4.46": 0.017287040129303932,
                    "5.90": 0.017717253416776657,
                    "4.31": 0.010665603913366795
                }
            },
            {
                "subject": "Brazil",
                "object": "4.31",
                "time": "2009",
                "probs": {
                    "8.94": 0.024722078815102577,
                    "6.00": 0.011926301755011082,
                    "7.67": 0.014886069111526012,
                    "8.44": 0.0035106991417706013,
                    "14.71": 0.7983646392822266,
                    "6.60": 0.026308884844183922,
                    "6.87": 0.008464953862130642,
                    "3.14": 0.006722384598106146,
                    "4.46": 0.039046403020620346,
                    "5.90": 0.041706353425979614,
                    "4.31": 0.02434120886027813
                }
            },
            {
                "subject": "South Korea",
                "object": "0.81",
                "time": "1999",
                "probs": {
                    "0.81": 0.016694888472557068,
                    "2.28": 0.09315071254968643,
                    "4.08": 0.0769905224442482,
                    "2.75": 0.15868334472179413,
                    "3.57": 0.1598498523235321,
                    "3.63": 0.07229059189558029,
                    "2.77": 0.09487786144018173,
                    "2.22": 0.05484618991613388,
                    "2.53": 0.12846256792545319,
                    "4.67": 0.03905471786856651,
                    "2.76": 0.10509876161813736
                }
            },
            {
                "subject": "South Korea",
                "object": "2.28",
                "time": "2000",
                "probs": {
                    "0.81": 0.010833429172635078,
                    "2.28": 0.057902976870536804,
                    "4.08": 0.07388126850128174,
                    "2.75": 0.1670844554901123,
                    "3.57": 0.17482668161392212,
                    "3.63": 0.10858631134033203,
                    "2.77": 0.08613575249910355,
                    "2.22": 0.04414615035057068,
                    "2.53": 0.11575368046760559,
                    "4.67": 0.03849291428923607,
                    "2.76": 0.1223563626408577
                }
            },
            {
                "subject": "South Korea",
                "object": "4.08",
                "time": "2001",
                "probs": {
                    "0.81": 0.01586664654314518,
                    "2.28": 0.07007639110088348,
                    "4.08": 0.09396917372941971,
                    "2.75": 0.14962710440158844,
                    "3.57": 0.19272251427173615,
                    "3.63": 0.10966680198907852,
                    "2.77": 0.07692278176546097,
                    "2.22": 0.041051775217056274,
                    "2.53": 0.09995947033166885,
                    "4.67": 0.07174532860517502,
                    "2.76": 0.07839208096265793
                }
            },
            {
                "subject": "South Korea",
                "object": "2.75",
                "time": "2002",
                "probs": {
                    "0.81": 0.01679261401295662,
                    "2.28": 0.0393778495490551,
                    "4.08": 0.10118129104375839,
                    "2.75": 0.14724712073802948,
                    "3.57": 0.18619035184383392,
                    "3.63": 0.12429380416870117,
                    "2.77": 0.08801452815532684,
                    "2.22": 0.03792916238307953,
                    "2.53": 0.10396313667297363,
                    "4.67": 0.05638594552874565,
                    "2.76": 0.09862425923347473
                }
            },
            {
                "subject": "South Korea",
                "object": "3.57",
                "time": "2003",
                "probs": {
                    "0.81": 0.01764361932873726,
                    "2.28": 0.03644178807735443,
                    "4.08": 0.13378959894180298,
                    "2.75": 0.10808110237121582,
                    "3.57": 0.20752748847007751,
                    "3.63": 0.13419237732887268,
                    "2.77": 0.06464116275310516,
                    "2.22": 0.02333391085267067,
                    "2.53": 0.08099780976772308,
                    "4.67": 0.10925006121397018,
                    "2.76": 0.0841011106967926
                }
            },
            {
                "subject": "South Korea",
                "object": "3.63",
                "time": "2004",
                "probs": {
                    "0.81": 0.013889455236494541,
                    "2.28": 0.050041135400533676,
                    "4.08": 0.17452086508274078,
                    "2.75": 0.12871700525283813,
                    "3.57": 0.16303910315036774,
                    "3.63": 0.09521530568599701,
                    "2.77": 0.06607761234045029,
                    "2.22": 0.029595734551548958,
                    "2.53": 0.09277647733688354,
                    "4.67": 0.07565958797931671,
                    "2.76": 0.11046769469976425
                }
            },
            {
                "subject": "South Korea",
                "object": "2.77",
                "time": "2005",
                "probs": {
                    "0.81": 0.02354379929602146,
                    "2.28": 0.031567517668008804,
                    "4.08": 0.17827002704143524,
                    "2.75": 0.08032318204641342,
                    "3.57": 0.25677838921546936,
                    "3.63": 0.09104030579328537,
                    "2.77": 0.05357130616903305,
                    "2.22": 0.020386498421430588,
                    "2.53": 0.06605792790651321,
                    "4.67": 0.12945756316184998,
                    "2.76": 0.06900348514318466
                }
            },
            {
                "subject": "South Korea",
                "object": "2.22",
                "time": "2006",
                "probs": {
                    "0.81": 0.0223496425896883,
                    "2.28": 0.031713906675577164,
                    "4.08": 0.3093191981315613,
                    "2.75": 0.07372242212295532,
                    "3.57": 0.16465838253498077,
                    "3.63": 0.08936762064695358,
                    "2.77": 0.04858870059251785,
                    "2.22": 0.023844130337238312,
                    "2.53": 0.046984683722257614,
                    "4.67": 0.10913769900798798,
                    "2.76": 0.08031363040208817
                }
            },
            {
                "subject": "South Korea",
                "object": "2.53",
                "time": "2007",
                "probs": {
                    "0.81": 0.024064339697360992,
                    "2.28": 0.030024968087673187,
                    "4.08": 0.32567328214645386,
                    "2.75": 0.06590759009122849,
                    "3.57": 0.15380781888961792,
                    "3.63": 0.0742020383477211,
                    "2.77": 0.033674634993076324,
                    "2.22": 0.02120966464281082,
                    "2.53": 0.05473193898797035,
                    "4.67": 0.16039183735847473,
                    "2.76": 0.056311849504709244
                }
            },
            {
                "subject": "South Korea",
                "object": "4.67",
                "time": "2008",
                "probs": {
                    "0.81": 0.0236614141613245,
                    "2.28": 0.0188923217356205,
                    "4.08": 0.34833118319511414,
                    "2.75": 0.06751833111047745,
                    "3.57": 0.1993548423051834,
                    "3.63": 0.08623018860816956,
                    "2.77": 0.03478224575519562,
                    "2.22": 0.019809257239103317,
                    "2.53": 0.043236374855041504,
                    "4.67": 0.12277774512767792,
                    "2.76": 0.03540608286857605
                }
            },
            {
                "subject": "South Korea",
                "object": "2.76",
                "time": "2009",
                "probs": {
                    "0.81": 0.037771109491586685,
                    "2.28": 0.023859592154622078,
                    "4.08": 0.29472681879997253,
                    "2.75": 0.05956527218222618,
                    "3.57": 0.19500774145126343,
                    "3.63": 0.1420191079378128,
                    "2.77": 0.030951134860515594,
                    "2.22": 0.02288173697888851,
                    "2.53": 0.05003057420253754,
                    "4.67": 0.1030358374118805,
                    "2.76": 0.04015104100108147
                }
            }
        ]
    }
}